rbv_ut/__init__.py
rbv_ut/matakuliah.py
rbv_ut/mk/__init__.py
rbv_ut/mk/fe.py
rbv_ut/mk/fhisip.py
rbv_ut/mk/fkip.py
rbv_ut/mk/fst.py
rbv_ut/mk/pascasarjana.py
rbv_ut-0.1.0.dist-info/LICENSE
rbv_ut-0.1.0.dist-info/WHEEL
rbv_ut-0.1.0.dist-info/METADATA
rbv_ut-0.1.0.dist-info/RECORD
